Metadata-Version: 2.1
Name: TOPSIS-Ritik-102053036
Version: 0.1
Summary: Compute Topsis Scores/Ranks of a given csv file
Home-page: https://github.com/ritikarora995/Topsis
Download-URL: https://github.com/ritikarora995/Topsis/archive/refs/tags/setup.py.tar.gz
Author: Ritik arora
Author-email: ritikarora995@gmail.com
License: MIT
Keywords: SOME,MEANINGFULL,KEYWORDS
Classifier: Development Status :: 3 - Alpha
Classifier: Intended Audience :: Developers
Classifier: Topic :: Software Development :: Build Tools
Classifier: License :: OSI Approved :: MIT License
Classifier: Programming Language :: Python :: 3
Classifier: Programming Language :: Python :: 3.4
Classifier: Programming Language :: Python :: 3.5
Classifier: Programming Language :: Python :: 3.6
